enriched_progress/__init__.py
enriched_progress/progress.py
enriched_progress/py.typed
enriched_progress/examples/both.py
enriched_progress/examples/multiple_calls_to_multiprogress.py
enriched_progress/examples/processes.py
enriched_progress/examples/threads.py
enriched_progress/examples/using_other_rich_features.py
multiprog-1.0.0.dist-info/METADATA
multiprog-1.0.0.dist-info/WHEEL
multiprog-1.0.0.dist-info/entry_points.txt
multiprog-1.0.0.dist-info/RECORD
