Metadata-Version: 2.4
Name: multiprog
Version: 1.0.0
Summary: Simple to use progress bar with subprocesses and threads.
Requires-Python: >=3.10
Requires-Dist: filelock
Requires-Dist: rich>=13.8.0
Requires-Dist: tenacity
